aapi/__init__.py
aapi/action.py
aapi/addevents.py
aapi/ai.py
aapi/basefolder.py
aapi/bases.py
aapi/businessfield.py
aapi/businessparameter.py
aapi/calendar.py
aapi/calendarfields.py
aapi/calendarkey.py
aapi/captureoutput.py
aapi/condition.py
aapi/config.py
aapi/connectionprofile.py
aapi/ctbruledata.py
aapi/date.py
aapi/definitionitemdetails.py
aapi/deleteevents.py
aapi/disallowedoptions.py
aapi/do.py
aapi/donotify.py
aapi/driver.py
aapi/endpoint.py
aapi/event.py
aapi/extractrule.py
aapi/filetransfer.py
aapi/filetransfergroup.py
aapi/flow.py
aapi/folderclientdata.py
aapi/folderjobbase.py
aapi/hostfiletransfer.py
aapi/hostmapping.py
aapi/if_.py
aapi/ifbase.py
aapi/ifcollection.py
aapi/ifrerun.py
aapi/internalrule.py
aapi/iteminfo.py
aapi/job.py
aapi/jobsfilter.py
aapi/jobtag.py
aapi/mail.py
aapi/notify.py
aapi/on.py
aapi/output.py
aapi/package.py
aapi/packageparams.py
aapi/period.py
aapi/possibleoptions.py
aapi/propertycondition.py
aapi/rbcdetails.py
aapi/remedy.py
aapi/resource.py
aapi/resourcepools.py
aapi/run.py
aapi/runningjobs.py
aapi/set_.py
aapi/sitestandard.py
aapi/sitestandarddata.py
aapi/sitestandardoperatorvalueoptions.py
aapi/sitestandardpolicy.py
aapi/sitestandardpolicydata.py
aapi/sitestandardpossiblevalue.py
aapi/sitestandardrestriction.py
aapi/steprange.py
aapi/tag.py
aapi/time.py
aapi/variable.py
aapi/waitforevents.py
aapi/workloadflat.py
aapi/workloadpolicy.py
aapi/wpperiod.py
aapi/year.py
aapi/integration_factory/__init__.py
aapi/integration_factory/connection_profiles.py
aapi/integration_factory/jobs.py
aapi/utils/__init__.py
aapi/utils/converter/__init__.py
aapi/utils/converter/discovery.py
aapi/utils/converter/job_type_registry.py
aapi/utils/converter/registry.py
aapi/utils/converter/shared_converter.py
clients/__init__.py
clients/ctm_api_client/__init__.py
clients/ctm_api_client/api_client.py
clients/ctm_api_client/configuration.py
clients/ctm_api_client/exceptions.py
clients/ctm_api_client/rest.py
clients/ctm_api_client/api/__init__.py
ctm_python_client-2.5.10.dist-info/licenses/LICENSE
ctm_python_client-2.5.10.dist-info/METADATA
ctm_python_client-2.5.10.dist-info/WHEEL
ctm_python_client-2.5.10.dist-info/top_level.txt
ctm_python_client-2.5.10.dist-info/RECORD
