Metadata-Version: 2.4
Name: ctm-python-client
Version: 2.5.10
Summary: Python Workflows for Control-M
Author: BMC Software
License: BSD 3-Clause
Keywords: Control-M
Classifier: Development Status :: 5 - Production/Stable
Classifier: Intended Audience :: Developers
Classifier: Programming Language :: Python :: 3
License-File: LICENSE
Requires-Dist: requests>=2.23.0
Requires-Dist: urllib3
Requires-Dist: six
Requires-Dist: attrs
Requires-Dist: certifi
Requires-Dist: jinja2
Requires-Dist: cattrs>=24.1.3
Dynamic: author
Dynamic: classifier
Dynamic: description
Dynamic: description-content-type
Dynamic: keywords
Dynamic: license
Dynamic: license-file
Dynamic: requires-dist
Dynamic: summary
